ak_video_analyser/__init__.py
ak_video_analyser/__main__.py
ak_video_analyser/ak_video_analyser_cmd.py
ak_video_analyser/ak_video_analyser/conf/my_app_config.conf
ak_video_analyser/ak_video_analyser/conf/trained_model/YOLOv8/best.pt
camera_management_s/__init__.py
camera_management_s/camera_parameters.py
camera_management_s/camera_parameters_selector.py
camera_management_s/test/__init__.py
camera_management_s/test/test_calibration.py
camera_management_s/test/test_camera_parameters.py
data_features_processor/__init__.py
data_features_processor/data_features_config.py
data_features_processor/features_extraction.py
data_features_processor/test/__init__.py
data_features_processor/test/test_data_feature_config.py
data_features_processor/test/test_features_extraction.py
data_features_processor/test/test_features_extraction_mask.py
dataset_management/__init__.py
dataset_management/dataset_config.py
dataset_management/dataset_manager.py
dataset_management/filename_decoder.py
dataset_management/pascal_voc_parser.py
dataset_management/test/__init__.py
dataset_management/test/test_dataset_config.py
dataset_management/test/test_dataset_manager.py
dataset_management/test/test_filename_decoder.py
dataset_management/test/test_pascal_voc_parser.py
dataset_management/test/test_suite_dataset_management.py
depth_estimation_s/__init__.py
depth_estimation_s/depth_estimation_methods.py
depth_estimation_s/depth_estimation_methods_selector.py
depth_estimation_s/test/__init__.py
depth_estimation_s/test/test_depth_estimation.py
depth_estimation_s/test/test_depth_estimation_mask.py
filters_v/__init__.py
filters_v/depth_filter.py
filters_v/obj_filters.py
filters_v/obj_filters_02.py
filters_v/test/__init__.py
filters_v/test/test_depth_filter.py
filters_v/test/test_obj_filters.py
filters_v/test/test_obj_filters_02.py
gui_analyser/__init__.py
gui_analyser/gui_app_about_window.py
gui_analyser/gui_app_help_window.py
gui_analyser/gui_app_main_window_02.py
gui_analyser/gui_video_analyser_config.py
ak_video_analyser-0.0.2.dist-info/LICENSE
ak_video_analyser-0.0.2.dist-info/METADATA
ak_video_analyser-0.0.2.dist-info/WHEEL
ak_video_analyser-0.0.2.dist-info/top_level.txt
ak_video_analyser-0.0.2.dist-info/RECORD
