Metadata-Version: 2.1
Name: ak-video-analyser
Version: 0.0.2
Summary: AK_VIDEO_ANALYZER that analyses videos on which to automatically detect apples, estimate their size and predict yield at the plot or per hectare scale using the appropriate simulated algorithms.
Home-page: https://github.com/GRAP-UdL-AT/ak_video_analyser/
Author: Juan Carlos Miranda, Jaume Arno, Jordi Gene-Mola, Spyros Fountas, Eduard Gregorio
Author-email: juancarlos.miranda@udl.cat, jaume.arno@udl.cat, jordi.genemola@udl.cat, sfountas@aua.gr, eduard.gregorio@udl.cat
Project-URL: Bug Tracker, https://github.com/GRAP-UdL-AT/ak_video_analyser/issues/
Classifier: Programming Language :: Python :: 3
Classifier: License :: OSI Approved :: MIT License
Classifier: Operating System :: OS Independent
Requires-Python: >=3.8
License-File: LICENSE
Requires-Dist: pip ==23.2.1
Requires-Dist: altgraph ==0.17.3
Requires-Dist: bleach ==6.0.0
Requires-Dist: build ==0.10.0
Requires-Dist: certifi ==2022.12.7
Requires-Dist: charset-normalizer ==3.0.1
Requires-Dist: colorama ==0.4.6
Requires-Dist: contourpy ==1.1.0
Requires-Dist: cycler ==0.11.0
Requires-Dist: docutils ==0.19
Requires-Dist: fonttools ==4.40.0
Requires-Dist: future ==0.18.3
Requires-Dist: idna ==3.4
Requires-Dist: importlib-metadata ==6.0.0
Requires-Dist: importlib-resources ==5.12.0
Requires-Dist: jaraco.classes ==3.2.3
Requires-Dist: keyring ==23.13.1
Requires-Dist: kiwisolver ==1.4.4
Requires-Dist: lxml ==4.9.2
Requires-Dist: markdown-it-py ==2.2.0
Requires-Dist: matplotlib ==3.7.2
Requires-Dist: mdurl ==0.1.2
Requires-Dist: more-itertools ==9.1.0
Requires-Dist: numpy ==1.24.2
Requires-Dist: opencv-python ==4.7.0.68
Requires-Dist: packaging ==23.0
Requires-Dist: pandas ==1.5.3
Requires-Dist: pefile ==2022.5.30
Requires-Dist: Pillow ==9.4.0
Requires-Dist: pkginfo ==1.9.6
Requires-Dist: psutil ==5.9.5
Requires-Dist: Pygments ==2.14.0
Requires-Dist: pyinstaller ==5.7.0
Requires-Dist: pyinstaller-hooks-contrib ==2022.15
Requires-Dist: pyk4a ==1.5.0
Requires-Dist: pyparsing ==3.0.9
Requires-Dist: pyproject-hooks ==1.0.0
Requires-Dist: python-dateutil ==2.8.2
Requires-Dist: pytz ==2022.7.1
Requires-Dist: pywin32-ctypes ==0.2.0
Requires-Dist: PyYAML ==6.0
Requires-Dist: readme-renderer ==37.3
Requires-Dist: requests ==2.28.2
Requires-Dist: requests-toolbelt ==0.10.1
Requires-Dist: rfc3986 ==2.0.0
Requires-Dist: rich ==13.3.1
Requires-Dist: scipy ==1.10.1
Requires-Dist: seaborn ==0.12.2
Requires-Dist: six ==1.16.0
Requires-Dist: tomli ==2.0.1
Requires-Dist: torch ==1.13.1
Requires-Dist: torchaudio ==0.13.1
Requires-Dist: torchvision ==0.14.1
Requires-Dist: tqdm ==4.65.0
Requires-Dist: twine ==4.0.2
Requires-Dist: typing-extensions ==4.5.0
Requires-Dist: ultralytics ==8.0.128
Requires-Dist: urllib3 ==1.26.14
Requires-Dist: webencodings ==0.5.1
Requires-Dist: zipp ==3.14.0
